<tranSapo>
  <Recorridos>
    <Recorrido>
      <Numero>R001</Numero>
    </Recorrido>
    <Recorrido>
      <Numero>R002</Numero>
    </Recorrido>
  </Recorridos>
  <Paraderos>
    <Paradero>
      <Codigo>P100</Codigo>
    </Paradero>
    <Paradero>
      <Codigo>P101</Codigo>
    </Paradero>
    <Paradero>
      <Codigo>P102</Codigo>
    </Paradero>
    <Paradero>
      <Codigo>P103</Codigo>
    </Paradero>
    <Paradero>
      <Codigo>P104</Codigo>
    </Paradero>
    <Paradero>
      <Codigo>P105</Codigo>
    </Paradero>
    <Paradero>
      <Codigo>P106</Codigo>
    </Paradero>
    <Paradero>
      <Codigo>P107</Codigo>
    </Paradero>
    <Paradero>
      <Codigo>P108</Codigo>
    </Paradero>
    <Paradero>
      <Codigo>P109</Codigo>
    </Paradero>
  </Paraderos>
  <Cuentas>
    <Cuenta>
      <Username>muZk</Username>
      <Validado>True</Validado>
      <Validador>NEECO.GMZ@GMAIL.COM-A4BA8EDE-4852-41C4-997A-D8C02C1317CF</Validador>
      <Password>123456</Password>
      <Email>neeco.gmz@gmail.com</Email>
    </Cuenta>
  </Cuentas>
  <Estados>
    <Estado>
      <Nombre>Panne</Nombre>
    </Estado>
    <Estado>
      <Nombre>Vacío</Nombre>
    </Estado>
    <Estado>
      <Nombre>Lleno</Nombre>
    </Estado>
    <Estado>
      <Nombre>Detenido</Nombre>
    </Estado>
    <Estado>
      <Nombre>Problemas</Nombre>
    </Estado>
  </Estados>
  <RecorridosParaderos>
    <RecorridoParadero>
      <Recorrido>
        <Numero>R001</Numero>
      </Recorrido>
      <Paradero>
        <Codigo>P100</Codigo>
      </Paradero>
      <NumeroParada>
        <Parada>0</Parada>
      </NumeroParada>
    </RecorridoParadero>
    <RecorridoParadero>
      <Recorrido>
        <Numero>R001</Numero>
      </Recorrido>
      <Paradero>
        <Codigo>P101</Codigo>
      </Paradero>
      <NumeroParada>
        <Parada>1</Parada>
      </NumeroParada>
    </RecorridoParadero>
    <RecorridoParadero>
      <Recorrido>
        <Numero>R001</Numero>
      </Recorrido>
      <Paradero>
        <Codigo>P102</Codigo>
      </Paradero>
      <NumeroParada>
        <Parada>2</Parada>
      </NumeroParada>
    </RecorridoParadero>
    <RecorridoParadero>
      <Recorrido>
        <Numero>R001</Numero>
      </Recorrido>
      <Paradero>
        <Codigo>P103</Codigo>
      </Paradero>
      <NumeroParada>
        <Parada>3</Parada>
      </NumeroParada>
    </RecorridoParadero>
    <RecorridoParadero>
      <Recorrido>
        <Numero>R001</Numero>
      </Recorrido>
      <Paradero>
        <Codigo>P104</Codigo>
      </Paradero>
      <NumeroParada>
        <Parada>4</Parada>
      </NumeroParada>
    </RecorridoParadero>
    <RecorridoParadero>
      <Recorrido>
        <Numero>R002</Numero>
      </Recorrido>
      <Paradero>
        <Codigo>P100</Codigo>
      </Paradero>
      <NumeroParada>
        <Parada>0</Parada>
      </NumeroParada>
    </RecorridoParadero>
    <RecorridoParadero>
      <Recorrido>
        <Numero>R002</Numero>
      </Recorrido>
      <Paradero>
        <Codigo>P102</Codigo>
      </Paradero>
      <NumeroParada>
        <Parada>1</Parada>
      </NumeroParada>
    </RecorridoParadero>
    <RecorridoParadero>
      <Recorrido>
        <Numero>R002</Numero>
      </Recorrido>
      <Paradero>
        <Codigo>P104</Codigo>
      </Paradero>
      <NumeroParada>
        <Parada>2</Parada>
      </NumeroParada>
    </RecorridoParadero>
    <RecorridoParadero>
      <Recorrido>
        <Numero>R002</Numero>
      </Recorrido>
      <Paradero>
        <Codigo>P106</Codigo>
      </Paradero>
      <NumeroParada>
        <Parada>3</Parada>
      </NumeroParada>
    </RecorridoParadero>
  </RecorridosParaderos>
  <Informaciones>
    <Informacion>
      <Nombre>Vacío</Nombre>
      <Codigo>P100</Codigo>
      <Numero>R001</Numero>
      <Fecha>06-06-2012 11:37:45</Fecha>
    </Informacion>
    <Informacion>
      <Nombre>Vacío</Nombre>
      <Codigo>P101</Codigo>
      <Numero>R001</Numero>
      <Fecha>06-06-2012 11:38:05</Fecha>
    </Informacion>
    <Informacion>
      <Nombre>Vacío</Nombre>
      <Codigo>P102</Codigo>
      <Numero>R001</Numero>
      <Fecha>06-06-2012 11:38:20</Fecha>
    </Informacion>
    <Informacion>
      <Nombre>Vacío</Nombre>
      <Codigo>P103</Codigo>
      <Numero>R001</Numero>
      <Fecha>06-06-2012 11:38:28</Fecha>
    </Informacion>
    <Informacion>
      <Nombre>Lleno</Nombre>
      <Codigo>P103</Codigo>
      <Numero>R001</Numero>
      <Fecha>06-06-2012 11:38:42</Fecha>
    </Informacion>
    <Informacion>
      <Nombre>Vacío</Nombre>
      <Codigo>P104</Codigo>
      <Numero>R001</Numero>
      <Fecha>06-06-2012 11:39:05</Fecha>
    </Informacion>
    <Informacion>
      <Nombre>Vacío</Nombre>
      <Codigo>P100</Codigo>
      <Numero>R001</Numero>
      <Fecha>15-06-2012 17:45:59</Fecha>
    </Informacion>
  </Informaciones>
</tranSapo>